energyid/__init__.py
energyid/asyncclient.py
energyid/client.py
energyid/misc.py
energyid/models.py
energyid/pandasclient.py
energyid/webhooks/__init__.py
EnergyID-0.0.17.dist-info/LICENSE
EnergyID-0.0.17.dist-info/METADATA
EnergyID-0.0.17.dist-info/WHEEL
EnergyID-0.0.17.dist-info/top_level.txt
EnergyID-0.0.17.dist-info/RECORD
