Metadata-Version: 2.1
Name: EnergyID
Version: 0.0.17
Summary: A python API wrapper for EnergyID
Home-page: https://github.com/EnergieID/energyid-py
Author: EnergieID.be
Author-email: jan@energieid.be
License: MIT
Keywords: EnergyID API Webhooks Python
Classifier: Development Status :: 3 - Alpha
Classifier: Intended Audience :: Developers
Classifier: Topic :: Scientific/Engineering
Classifier: License :: OSI Approved :: MIT License
Classifier: Programming Language :: Python :: 3
License-File: LICENSE
Requires-Dist: requests
Requires-Dist: pandas
